main.py
dfadsfsfasdfa-0.1.0.dist-info/METADATA
dfadsfsfasdfa-0.1.0.dist-info/WHEEL
dfadsfsfasdfa-0.1.0.dist-info/top_level.txt
dfadsfsfasdfa-0.1.0.dist-info/RECORD
