Metadata-Version: 2.1
Name: dfadsfsfasdfa
Version: 0.1.0
Summary: A brief description of your package
Author: hrewew
